README.txt
bootstrap.py
buildout-3.0.cfg
buildout.cfg
setup.cfg
setup.py
Products/__init__.py
Products.PloneSubSkins.egg-info/PKG-INFO
Products.PloneSubSkins.egg-info/SOURCES.txt
Products.PloneSubSkins.egg-info/dependency_links.txt
Products.PloneSubSkins.egg-info/entry_points.txt
Products.PloneSubSkins.egg-info/namespace_packages.txt
Products.PloneSubSkins.egg-info/not-zip-safe
Products.PloneSubSkins.egg-info/requires.txt
Products.PloneSubSkins.egg-info/top_level.txt
Products/PloneSubSkins/AppConfig.py
Products/PloneSubSkins/SubSkinsTool.py
Products/PloneSubSkins/__init__.py
Products/PloneSubSkins/config.py
Products/PloneSubSkins/configure.zcml
Products/PloneSubSkins/install.txt
Products/PloneSubSkins/interfaces.py
Products/PloneSubSkins/profiles.zcml
Products/PloneSubSkins/setuphandlers.py
Products/PloneSubSkins/styles.py
Products/PloneSubSkins/tool.gif
Products/PloneSubSkins/browser/__init__.py
Products/PloneSubSkins/browser/configure.zcml
Products/PloneSubSkins/browser/plonesubskins_styles.css
Products/PloneSubSkins/browser/skin_form_load.js
Products/PloneSubSkins/browser/subskins_choice_form.pt
Products/PloneSubSkins/browser/viewlet.pt
Products/PloneSubSkins/browser/views.py
Products/PloneSubSkins/profiles/default/actions.xml
Products/PloneSubSkins/profiles/default/controlpanel.xml
Products/PloneSubSkins/profiles/default/cssregistry.xml
Products/PloneSubSkins/profiles/default/import_steps.xml
Products/PloneSubSkins/profiles/default/jsregistry.xml
Products/PloneSubSkins/profiles/default/metadata.xml
Products/PloneSubSkins/profiles/default/registry.xml
Products/PloneSubSkins/profiles/default/skins.xml
Products/PloneSubSkins/profiles/default/toolset.xml
Products/PloneSubSkins/profiles/default/types.xml
Products/PloneSubSkins/profiles/default/types/SubSkinsTool.xml
Products/PloneSubSkins/profiles/upgrade/metadata.xml
Products/PloneSubSkins/profiles/upgrade/registry.xml
Products/PloneSubSkins/profiles/upgrade/types/SubSkinsTool.xml
Products/PloneSubSkins/skins/plonesubskins_images/SubSkinsTool.gif
Products/PloneSubSkins/skins/plonesubskins_images/configlet.gif
Products/PloneSubSkins/skins/plonesubskins_images/ico_arrow_next.gif
Products/PloneSubSkins/skins/plonesubskins_images/ico_arrow_previous.gif
Products/PloneSubSkins/skins/plonesubskins_scripts/dim_to_black.py
Products/PloneSubSkins/skins/plonesubskins_scripts/dim_to_white.py
