Metadata-Version: 1.0
Name: Products.PloneSubSkins
Version: 4.7.5
Summary: Manage Plone skins CSS, logo, and base colors dynamically from the Plone control panel
Home-page: http://plone.org/products/subskins
Author: Eric BREHAULT
Author-email: eric.brehault@makina-corpus.org
License: ZPL
Keywords: plone skin skinning customization
Platform: UNKNOWN
Classifier: Framework :: Plone
Classifier: Programming Language :: Python
Classifier: Topic :: Software Development :: Libraries :: Python Modules
